neovim/__init__.py
neovim/api/__init__.py
pynvim/__init__.py
pynvim/_version.py
pynvim/compat.py
pynvim/util.py
pynvim/api/__init__.py
pynvim/api/buffer.py
pynvim/api/common.py
pynvim/api/nvim.py
pynvim/api/tabpage.py
pynvim/api/window.py
pynvim/msgpack_rpc/__init__.py
pynvim/msgpack_rpc/async_session.py
pynvim/msgpack_rpc/msgpack_stream.py
pynvim/msgpack_rpc/session.py
pynvim/msgpack_rpc/event_loop/__init__.py
pynvim/msgpack_rpc/event_loop/asyncio.py
pynvim/msgpack_rpc/event_loop/base.py
pynvim/plugin/__init__.py
pynvim/plugin/decorators.py
pynvim/plugin/host.py
pynvim/plugin/script_host.py
pynvim-0.5.2.dist-info/LICENSE
pynvim-0.5.2.dist-info/METADATA
pynvim-0.5.2.dist-info/WHEEL
pynvim-0.5.2.dist-info/top_level.txt
pynvim-0.5.2.dist-info/RECORD
